stactools/nrcan_landcover/__init__.py
stactools/nrcan_landcover/cog.py
stactools/nrcan_landcover/commands.py
stactools/nrcan_landcover/constants.py
stactools/nrcan_landcover/stac.py
stactools/nrcan_landcover/utils.py
stactools_nrcan_landcover-0.2.4.dist-info/LICENSE
stactools_nrcan_landcover-0.2.4.dist-info/METADATA
stactools_nrcan_landcover-0.2.4.dist-info/WHEEL
stactools_nrcan_landcover-0.2.4.dist-info/top_level.txt
stactools_nrcan_landcover-0.2.4.dist-info/RECORD
