Metadata-Version: 2.1
Name: stactools-nrcan-landcover
Version: 0.2.4
Summary: Collection of Land Cover products for Canada as produced by NRCan
Home-page: https://github.com/stactools-packages/stactools-nrcan-landcover
Author: stac-utils
Author-email: stac@radiant.earth
License: UNKNOWN
Project-URL: Documentation, https://stactools-package.readthedocs.io/en/latest/
Project-URL: Issues, https://github.com/stactools-packages/stactools-nrcan-landcover/issues
Keywords: stactools,pystac,catalog,STAC
Platform: UNKNOWN
Classifier: Development Status :: 4 - Beta
Classifier: License :: OSI Approved :: Apache Software License
Classifier: Programming Language :: Python :: 3.6
Classifier: Programming Language :: Python :: 3.7
Classifier: Programming Language :: Python :: 3.8
Classifier: Programming Language :: Python :: 3.9
License-File: LICENSE
Requires-Dist: pytz (~=2021.1)
Requires-Dist: stactools (~=0.2.1)
